{"1":{"Id":"1","Type":"2","Range":"1","Additional":"2","InitialJuedg":"0","Value1":"7","Value2":"1006|10","FailEffect":"0","PreEffect":"","AfterEffect":""},"2":{"Id":"2","Type":"2","Range":"1","Additional":"1","InitialJuedg":"0","Value1":"5","Value2":"Promote|LEVEL_Atk|2","FailEffect":"0","PreEffect":"0","AfterEffect":"0"},"3":{"Id":"3","Type":"2","Range":"1","Additional":"1","InitialJuedg":"0","Value1":"5","Value2":"Promote|LEVEL_Spd|1","FailEffect":"0","PreEffect":"0","AfterEffect":"0"},"4":{"Id":"4","Type":"2","Range":"1","Additional":"1","InitialJuedg":"0","Value1":"3","Value2":"DamageIncrease|30|3|true","SucEffect":"","FailEffect":"","PreEffect":"","AfterEffect":""},"5":{"Id":"5","Type":"2","Range":"1","Additional":"1","InitialJuedg":"null|null|15","Value1":"5","Value2":"Promote|LEVEL_spAtk|1","FailEffect":"0","PreEffect":"0","AfterEffect":"0"},"1001":{"Id":"1001","Type":"2","Range":"1","Additional":"2","InitialJuedg":"0","Value1":"5","Value2":"Remove|LEVEL_ALL","FailEffect":"0","PreEffect":"0","AfterEffect":"0"},"1002":{"Id":"1002","Type":"2","Range":"1","Additional":"1","InitialJuedg":"0","Value1":"1","Value2":"Self_Damage|0.5","FailEffect":"0","PreEffect":"0","AfterEffect":"0"},"1003":{"Id":"1003","Type":"2","Range":"1","Additional":"2","InitialJuedg":"0","Value1":"6","Value2":"","FailEffect":"","PreEffect":"","AfterEffect":""},"1004":{"Id":"1004","Type":"2","Range":"1","Additional":"2","InitialJuedg":"0","Value1":"2","Value2":"Fixed|Fixed_Number|1|100","FailEffect":"0","PreEffect":"1005","AfterEffect":"0"},"1005":{"Id":"1005","Type":"2","Range":"1","Additional":"2","InitialJuedg":"0","Value1":"2","Value2":"Fixed|Fixed_Number|1|50","FailEffect":"0","PreEffect":"0","AfterEffect":"0"},"1006":{"Id":"1006","Type":"2","Range":"1","Additional":"1","InitialJuedg":"0","Value1":"5","Value2":"Promote|LEVEL_ALL|1","FailEffect":"0","PreEffect":"0","AfterEffect":"0"},"1007":{"Id":"1007","Type":"2","Range":"1","Additional":"1","InitialJuedg":"0","Value1":"1","Value2":"Self_Max_Hp|0.34","FailEffect":"0","PreEffect":"0","AfterEffect":"0"},"1008":{"Id":"1008","Type":"2","Range":"1","Additional":"2","InitialJuedg":"Less_Hp|Self_Max_Hp|0.5","Value1":"2","Value2":"","FailEffect":"0","PreEffect":"0","AfterEffect":"0"},"1009":{"Id":"1009","Type":"2","Range":"3","Additional":"1","InitialJuedg":"Enemy_Dead","Value1":"5","Value2":"","FailEffect":"1010","PreEffect":"0","AfterEffect":"0"},"1010":{"Id":"1010","Type":"2","Range":"1","Additional":"1","InitialJuedg":"0","Value1":"3","Value2":"HurtReduce|100|0.5","FailEffect":"0","PreEffect":"","AfterEffect":""},"1011":{"Id":"1011","Type":"2","Range":"1","Additional":"2","InitialJuedg":"0","Value1":"6","Value2":"","FailEffect":"0","PreEffect":"1012","AfterEffect":""},"1012":{"Id":"1012","Type":"2","Range":"1","Additional":"2","InitialJuedg":"","Value1":"7","Value2":"1006|40","FailEffect":"0","PreEffect":"","AfterEffect":""},"2001":{"Id":"2001","Type":"1","Range":"1","Additional":"1","InitialJuedg":"0","Value1":"3","Value2":"1007","FailEffect":"0","PreEffect":"0","AfterEffect":"0"},"2002":{"Id":"2002","Type":"1","Range":"1","Additional":"1","InitialJuedg":"0","Value1":"3","Value2":"1007|1008","FailEffect":"0","PreEffect":"0","AfterEffect":"0"},"5001":{"Id":"5001","Type":"3","Range":"1","Additional":"1","InitialJuedg":"0","Value1":"","Value2":"1006|2002","SucEffect":"","FailEffect":"","PreEffect":"","AfterEffect":""}}